[
    { 
        "id": 1,
        "description" : "Get groceries",
        "tags"  : [ "shopping", "chores" ]
    },
    { 
        "id": 2,
        "description" : "Make up some new ToDos",
        "tags"  : [ "writing", "work" ]
    },
    {
        "id": 3,
        "description" : "Prep for Monday's class",
        "tags"  : [ "work", "teaching" ]
    },
    { 
        "id": 4,
        "description" : "Answer emails",
        "tags"  : [ "work" ]
    },
    { 
        "id": 5,
        "description" : "Take Gracie to the park",
        "tags"  : [ "chores", "pets" ]
    },
    { 
        "id": 6,
        "description" : "Finish writing this book",
        "tags"  : [ "writing", "work" ]
    }
]
